{ 
    "_id" : ObjectId("574dfbc29db3a71c102ef675"), 
    "Entities" : [
        {
            "attributes" : {
                "Host" : "host1", 
                "Project" : "demo", 
                "Name" : "vm1-host1"
            }, 
            "group" : "host1", 
            "id" : "1", 
            "object_name" : "vm1-host1", 
            "level" : NumberInt(7),
			"type": "instance"
        }, 
        {
            "attributes" : [
                {
                    "id" : "vNIC1"
                }
            ], 
            "group" : "host1", 
            "id" : "2", 
            "object_name" : "vNIC1-vm1-host1", 
            "level" : NumberInt(1),
			"type": "vnic"
        }, 
        {
            "attributes" : {
                "Host" : "host1", 
                "Project" : "demo", 
                "Name" : "vm100-host1"
            }, 
            "group" : "host1", 
            "id" : "101", 
            "object_name" : "vm100-host1", 
            "level" : NumberInt(7),
			"type": "instance"
        }, 
        {
            "attributes" : [
                {
                    "id" : "vNIC1"
                    
                }
            ], 
            "group" : "host1", 
            "id" : "102", 
            "object_name" : "vNIC1-vm100-host1", 
            "level" : NumberInt(1),
			"type": "vnic"
        }, 
        {
            "attributes" : [
                {
                    "id" : "vConnector-Bridge"
                    
                }
            ], 
            "group" : "host1", 
            "id" : "3", 
            "object_name" : "vConnector1-host1",
            "level" : NumberInt(1),
			"type": "vconnector"
        }, 
        {
            "attributes" : {
                "ID" : "vEdge-OVS"
                
            }, 
            "group" : "host1", 
            "id" : "4", 
            "object_name" : "vEdge1-host1",
            "level" : NumberInt(1),
			"type": "vedge"
        }, 
        {
            "attributes" : {
                "ID" : "pNIC-eth0" 
                
            }, 
            "group" : "host1", 
            "id" : "5", 
            "object_name" : "pNIC:eth0-host1", 
            "level" : NumberInt(1),
			"type": "pnic"
        }, 
        {
            "attributes" : {
                "ID" : "Network100-segment-VLAN100", 
                "type" : "network"
            }, 
            "id" : "6", 
            "object_name" : "Network100", 
            "level" : NumberInt(1),
			"type" : "network"
        }, 
        {
            "attributes" : {
                "ID" : "Network200-segment-VLAN120", 
                "type" : "network"
            }, 
            "id" : "200", 
            "object_name" : "Network200", 
            "level" : NumberInt(1),
			"type" : "network"
        }, 
        {
            "attributes" : {
                "ID" : "Network300-segment-VLAN130", 
                "type" : "network"
            }, 
            "id" : "300", 
            "object_name" : "Network300", 
            "level" : NumberInt(1),
			"type" : "network"
        }, 
        {
            "attributes" : {
                "Host" : "host3", 
                "Project" : "coka-cola", 
                "Name" : "vm1-host3"
            }, 
            "group" : "host3", 
            "id" : "301", 
            "object_name" : "vm1-host3", 
            "level" : NumberInt(7),
			"type": "instance"
        }, 
        {
            "attributes" : [
                {
                    "id" : "vNIC1" 
                    
                }
            ], 
            "group" : "host3", 
            "id" : "302", 
            "object_name" : "vNIC1-vm1-host3", 
            "level" : NumberInt(1),
			"type": "vnic"
        }, 
        {
            "attributes" : [
                {
                    "id" : "vConnector-Bridge" 
                    
                }
            ], 
            "group" : "host3", 
            "id" : "303", 
            "object_name" : "vConnector1-host3", 
            "level" : NumberInt(1),
			"type": "vconnector"
        }, 
        {
            "attributes" : {
                "ID" : "vEdge-OVS" 
                
            }, 
            "group" : "host3", 
            "id" : "304", 
            "object_name" : "vEdge1-host3", 
            "level" : NumberInt(1),
			"type": "vedge"
        }, 
        {
            "attributes" : {
                "ID" : "pNIC-eth1" 
                
            }, 
            "group" : "host3", 
            "id" : "305", 
            "object_name" : "pNIC:eth1-host3", 
            "level" : NumberInt(1),
			"type": "pnic"
        }, 
        {
            "attributes" : [
                {
                    "id" : "vNIC2" 
                    
                }
            ], 
            "group" : "host3", 
            "id" : "3002", 
            "object_name" : "vNIC2-vm1-host3", 
            "level" : NumberInt(1),
			"type": "vnic"
        }, 
        {
            "attributes" : [
                {
                    "id" : "vConnector-Bridge" 
                    
                }
            ], 
            "group" : "host3", 
            "id" : "3003", 
            "object_name" : "vConnector2-host3", 
            "level" : NumberInt(1),
			"type": "vconnector"
        }, 
        {
            "attributes" : {
                "ID" : "vEdge-OVS" 
                
            }, 
            "group" : "host3", 
            "id" : "3004", 
            "object_name" : "vEdge2-host3", 
            "level" : NumberInt(1),
			"type": "vedge"
        }, 
        {
            "attributes" : {
                "ID" : "pNIC-eth2" 
                
            }, 
            "group" : "host3", 
            "id" : "3005", 
            "object_name" : "pNIC:eth2-host3", 
            "level" : NumberInt(1),
			"type": "pnic"
        }, 
        {
            "attributes" : [
                {
                    "id" : "DHCP-Network100" 
                    
                }
            ], 
            "group" : "host8", 
            "id" : "1002", 
            "object_name" : "vService-DHCP-Net100-Host8", 
            "level" : NumberInt(1),
			"type" : "vservice"
        }, 
        {
            "attributes" : [
                {
                    "id" : "vNIC1-host8" 
                    
                }
            ], 
            "group" : "host8", 
            "id" : "1003", 
            "object_name" : "DHCP-vNIC1-host8", 
            "level" : NumberInt(1),
			"type": "vnic"
        }, 
        {
            "attributes" : {
                "ID" : "vEdge"
                
            }, 
            "group" : "host8", 
            "id" : "1004", 
            "object_name" : "vEdge1-host8", 
            "level" : NumberInt(1),
			"type": "vedge"
        }, 
        {
            "attributes" : {
                "ID" : "pNIC-eth1", 
                
            }, 
            "group" : "host8", 
            "id" : "1005", 
            "object_name" : "pNIC:eth1-host8", 
            "level" : NumberInt(1),
			"type": "pnic"
        }, 
        {
            "attributes" : [
                {
                    "id" : "Router Net100-to-Net200" 
                    
                }
            ], 
            "group" : "host7", 
            "id" : "1112", 
            "object_name" : "vService Router Net100-to-Net200 Host7", 
            "level" : NumberInt(1),
			"type" : "vservice"
        }, 
        {
            "attributes" : [
                {
                    "id" : "vNIC1-host7" 
                    
                }
            ], 
            "group" : "host7", 
            "id" : "1113", 
            "object_name" : "Router-vNIC1-host7", 
            "level" : NumberInt(1),
			"type": "vnic"
        }, 
        {
            "attributes" : {
                "ID" : "vEdge-OVS" 
                
            }, 
            "group" : "host7", 
            "id" : "1114", 
            "object_name" : "vEdge1-host7", 
            "level" : NumberInt(1),
			"type": "vedge"
        }, 
        {
            "attributes" : {
                "ID" : "pNIC-eth1" 
                
            }, 
            "group" : "host7", 
            "id" : "1115", 
            "object_name" : "pNIC:eth1-host7", 
            "level" : NumberInt(1),
			"type": "pnic"
        }, 
        {
            "attributes" : [
                {
                    "id" : "vNIC2-host7" 
                    
                }
            ], 
            "group" : "host7", 
            "id" : "1213", 
            "object_name" : "Router-vNIC2-host7", 
            "level" : NumberInt(1),
			"type": "vnic"
        }, 
        {
            "attributes" : {
                "ID" : "vEdge-OVS" 
                
            }, 
            "group" : "host7", 
            "id" : "1214", 
            "object_name" : "vEdge2-host7", 
            "level" : NumberInt(1),
			"type": "vedge"
        }, 
        {
            "attributes" : {
                "ID" : "pNIC-eth2" 
                
            }, 
            "group" : "host7", 
            "id" : "1215", 
            "object_name" : "pNIC:eth2-host7", 
            "level" : NumberInt(1),
			"type": "pnic"
        }, 
        {
            "attributes" : {
                "Host" : "host20", 
                "Project" : "demo", 
                "Name" : "DHCP-Network200-host20", 
                
            }, 
            "group" : "host20", 
            "id" : "2001", 
            "object_name" : "vService-DHCP-Net200-host20", 
            "level" : NumberInt(7),
			"type" : "vservice"
        }, 
        {
            "attributes" : [
                {
                    "id" : "DHCP-Net200-vNIC1" 
                    
                }
            ], 
            "group" : "host20", 
            "id" : "2002", 
            "object_name" : "DHCP-Net200-vNIC1", 
            "level" : NumberInt(1),
			"type": "vnic"
        }, 
        {
            "attributes" : [
                {
                    "id" : "vConnector-Bridge" 
                    
                }
            ], 
            "group" : "host20", 
            "id" : "2003", 
            "object_name" : "vConnector209-host20", 
            "level" : NumberInt(1),
			"type": "vconnector"
        }, 
        {
            "attributes" : {
                "ID" : "vEdge-OVS" 
                
            }, 
            "group" : "host20", 
            "id" : "2004", 
            "object_name" : "vEdge1-host20", 
            "level" : NumberInt(1),
			"type": "vedge"
        }, 
        {
            "attributes" : {
                "ID" : "pNIC-eth0" 
                
            }, 
            "group" : "host20", 
            "id" : "2005", 
            "object_name" : "pNIC:eth0-host20", 
            "level" : NumberInt(1),
			"type": "pnic"
        }, 
        {
            "attributes" : {
                "Host" : "host2", 
                "Project" : "pepsi", 
                "Name" : "vm1-host2", 
                
            }, 
            "group" : "host2", 
            "id" : "401", 
            "object_name" : "vm1-host2", 
            "level" : NumberInt(7),
			"type": "instance"
        }, 
        {
            "attributes" : [
                {
                    "id" : "vNIC1" 
                    
                }
            ], 
            "group" : "host2", 
            "id" : "402", 
            "object_name" : "vNIC1-vm1-host2", 
            "level" : NumberInt(1),
			"type": "vnic"
        }, 
        {
            "attributes" : [
                {
                    "id" : "vConnector-Bridge" 
                    
                }
            ], 
            "group" : "host2", 
            "id" : "403", 
            "object_name" : "vConnector1-host2", 
            "level" : NumberInt(1),
			"type": "vconnector"
        }, 
        {
            "attributes" : {
                "ID" : "vEdge-OVS", 
                
            }, 
            "group" : "host2", 
            "id" : "404", 
            "object_name" : "vEdge1-host2", 
            "level" : NumberInt(1),
			"type": "vedge"
        }, 
        {
            "attributes" : {
                "ID" : "pNIC-eth0" 
                
            }, 
            "group" : "host2", 
            "id" : "405", 
            "object_name" : "pNIC:eth0-host2", 
            "level" : NumberInt(1),
			"type": "pnic"
        }, 
        {
            "attributes" : {
                "Host" : "host2", 
                "Project" : "coke", 
                "Name" : "vm7-host2" 
                
            }, 
            "group" : "host2", 
            "id" : "421", 
            "object_name" : "vm7-host2", 
            "level" : NumberInt(7),
			"type": "instance"
        }, 
        {
            "attributes" : [
                {
                    "id" : "vNIC1"
                    
                }
            ], 
            "group" : "host2", 
            "id" : "422", 
            "object_name" : "vNIC1-vm7-host2", 
            "level" : NumberInt(1),
			"type": "vnic"
        }, 
        {
            "attributes" : [
                {
                    "id" : "vConnector-Bridge" 
                    
                }
            ], 
            "group" : "host2", 
            "id" : "423", 
            "object_name" : "vConnector2-host2", 
            "level" : NumberInt(1),
			"type": "vconnector"
        }, 
        {
            "attributes" : {
                "ID" : "vEdge-OVS" 
                
            }, 
            "group" : "host2", 
            "id" : "424", 
            "object_name" : "vEdge1-host2", 
            "level" : NumberInt(1),
			"type": "vedge"
        }, 
        {
            "attributes" : {
                "ID" : "pNIC-eth1" 
                
            }, 
            "group" : "host2", 
            "id" : "425", 
            "object_name" : "pNIC:eth1-host2", 
            "level" : NumberInt(1),
			"type": "pnic"
        }, 
        {
            "attributes" : {
                "Host" : "host24", 
                "Project" : "pepsi", 
                "Name" : "vm4-host24" 
                
            }, 
            "group" : "host24", 
            "id" : "501", 
            "object_name" : "vm4-host24", 
            "level" : NumberInt(7),
			"type": "instance"
        }, 
        {
            "attributes" : [
                {
                    "id" : "vNIC1" 
                    
                }
            ], 
            "group" : "host24", 
            "id" : "502", 
            "object_name" : "vNIC1-vm4-host24", 
            "level" : NumberInt(1),
			"type": "vnic"
        }, 
        {
            "attributes" : [
                {
                    "id" : "vConnector-Bridge" 
                    
                }
            ], 
            "group" : "host24", 
            "id" : "503", 
            "object_name" : "vConnector1-host24", 
            "level" : NumberInt(1),
			"type": "vconnector"
        }, 
        {
            "attributes" : {
                "ID" : "vEdge-OVS" 
                
            }, 
            "group" : "host24", 
            "id" : "504", 
            "object_name" : "vEdge1-host24", 
            "level" : NumberInt(1),
			"type": "vedge"
        }, 
        {
            "attributes" : {
                "ID" : "pNIC-eth0"
                
            }, 
            "group" : "host24", 
            "id" : "505", 
            "object_name" : "pNIC:eth0-host24", 
            "level" : NumberInt(1),
			"type": "pnic"
        }, 
        {
            "attributes" : {
                "Host" : "host24", 
                "Project" : "pepsi", 
                "Name" : "vm5-host24" 
                
            }, 
            "group" : "host24", 
            "id" : "601", 
            "object_name" : "vm5-host24", 
            "level" : NumberInt(7),
			"type": "instance"
        }, 
        {
            "attributes" : [
                {
                    "id" : "vNIC1"
                    
                }
            ], 
            "group" : "host24", 
            "id" : "602", 
            "object_name" : "vNIC1-vm5-host24", 
            "level" : NumberInt(1),
			"type": "vnic"
        }, 
        {
            "attributes" : {
                "Host" : "host24", 
                "Project" : "pepsi", 
                "Name" : "vm6-host24" 
                
            }, 
            "group" : "host24", 
            "id" : "701", 
            "object_name" : "vm6-host24", 
            "level" : NumberInt(7),
			"type": "instance"
        }, 
        {
            "attributes" : [
                {
                    "id" : "vNIC1" 
                    
                }
            ], 
            "group" : "host24", 
            "id" : "702", 
            "object_name" : "vNIC1-vm6-host24", 
            "level" : NumberInt(1),
			"type": "vnic"
        }, 
        {
            "attributes" : {
                "Host" : "host24", 
                "Project" : "pepsi", 
                "Name" : "vm7-host24"
                
            }, 
            "group" : "host24", 
            "id" : "801", 
            "object_name" : "vm7-host24", 
            "level" : NumberInt(7),
			"type": "instance"
        }, 
        {
            "attributes" : [
                {
                    "id" : "vNIC1" 
                    
                }
            ], 
            "group" : "host24", 
            "id" : "802", 
            "object_name" : "vNIC1-vm7-host24", 
            "level" : NumberInt(1),
			"type": "vnic"
        }, 
        {
            "attributes" : {
                "Host" : "host100", 
                "Project" : "OSDNA-ltd", 
                "Name" : "vm1-host100" 
                
            }, 
            "group" : "host100", 
            "id" : "4001", 
            "object_name" : "vm1-host100", 
            "level" : NumberInt(7),
			"type": "instance"
        }, 
        {
            "attributes" : [
                {
                    "id" : "vNIC1" 
                    
                }
            ], 
            "group" : "host100", 
            "id" : "4002", 
            "object_name" : "vNIC1-vm1-host100", 
            "level" : NumberInt(1),
			"type": "vnic"
        }, 
        {
            "attributes" : [
                {
                    "id" : "vConnector-Bridge" 
                    
                }
            ], 
            "group" : "host100", 
            "id" : "4003", 
            "object_name" : "vConnector1-host100", 
            "level" : NumberInt(1),
			"type": "vconnector"
        }, 
        {
            "attributes" : {
                "ID" : "vEdge-OVS" 
                
            }, 
            "group" : "host100", 
            "id" : "4004", 
            "object_name" : "vEdge1-host100", 
            "level" : NumberInt(1),
			"type": "vedge"
        }, 
        {
            "attributes" : {
                "ID" : "pNIC-eth0" 
                
            }, 
            "group" : "host100", 
            "id" : "4005", 
            "object_name" : "pNIC:eth0-host100", 
            "level" : NumberInt(1),
			"type": "pnic"
        }, 
        {
            "attributes" : {
                "Host" : "host200", 
                "Project" : "OSDNA-ltd", 
                "Name" : "vm4-host200"
                
            }, 
            "group" : "host200", 
            "id" : "5001", 
            "object_name" : "vm4-host200", 
            "level" : NumberInt(7),
			"type": "instance"
        }, 
        {
            "attributes" : [
                {
                    "id" : "vNIC1" 
                    
                }
            ], 
            "group" : "host200", 
            "id" : "5002", 
            "object_name" : "vNIC1-vm4-host200", 
            "level" : NumberInt(1),
			"type": "vnic"
        }, 
        {
            "attributes" : [
                {
                    "id" : "vConnector-Bridge" 
                    
                }
            ], 
            "group" : "host200", 
            "id" : "5003", 
            "object_name" : "vConnector1-host200", 
            "level" : NumberInt(1),
			"type": "vconnector"
        }, 
        {
            "attributes" : {
                "ID" : "vEdge-OVS" 
                
            }, 
            "group" : "host200", 
            "id" : "5004", 
            "object_name" : "vEdge1-host200", 
            "level" : NumberInt(1),
			"type": "vedge"
        }, 
        {
            "attributes" : {
                "ID" : "pNIC-eth0" 
                
            }, 
            "group" : "host200", 
            "id" : "5005", 
            "object_name" : "pNIC:eth0-host200", 
            "level" : NumberInt(1),
			"type": "pnic"
        }, 
        {
            "attributes" : {
                "Host" : "host200", 
                "Project" : "OSDNA-ltd", 
                "Name" : "vm5-host200" 
                
            }, 
            "group" : "host200", 
            "id" : "6001", 
            "object_name" : "vm5-host200", 
            "level" : NumberInt(7),
			"type": "instance"
        }, 
        {
            "attributes" : [
                {
                    "id" : "vNIC1" 
                    
                }
            ], 
            "group" : "host200", 
            "id" : "6002", 
            "object_name" : "vNIC1-vm5-host200", 
            "level" : NumberInt(1),
			"type": "vnic"
        }, 
        {
            "attributes" : {
                "Host" : "host200", 
                "Project" : "OSDNA-ltd", 
                "Name" : "vm6-host200" 
                
            }, 
            "group" : "host200", 
            "id" : "7001", 
            "object_name" : "vm6-host200", 
            "level" : NumberInt(7),
			"type": "instance"
        }, 
        {
            "attributes" : [
                {
                    "id" : "vNIC1" 
                    
                }
            ], 
            "group" : "host200", 
            "id" : "7002", 
            "object_name" : "vNIC1-vm6-host200", 
            "level" : NumberInt(1),
			"type": "vnic"
        }, 
        {
            "attributes" : {
                "Host" : "host200", 
                "Project" : "OSDNA-ltd", 
                "Name" : "vm7-host200" 
                
            }, 
            "group" : "host200", 
            "id" : "8001", 
            "object_name" : "vm7-host200", 
            "level" : NumberInt(7),
			"type": "instance"
        }, 
        {
            "attributes" : [
                {
                    "id" : "vNIC1" 
                    
                }
            ], 
            "group" : "host200", 
            "id" : "8002", 
            "object_name" : "vNIC1-vm7-host200", 
            "level" : NumberInt(1),
			"type": "vnic"
        }, 
        {
            "attributes" : {
                "Host" : "host200", 
                "Project" : "OSDNA-ltd", 
                "Name" : "vm8-host200" 
                
            }, 
            "group" : "host200", 
            "id" : "9001", 
            "object_name" : "vm8-host200", 
            "level" : NumberInt(7),
			"type": "instance"
        }, 
        {
            "attributes" : [
                {
                    "id" : "vNIC1" 
                    
                }
            ], 
            "group" : "host200", 
            "id" : "9002", 
            "object_name" : "vNIC1-vm8-host200", 
            "level" : NumberInt(1),
			"type": "vnic"
        }
    ], 
    "Relations" : [
        {
            "attributes" : {
                "VLAN vid" : "5", 
                "IP address" : "192.168.77.1", 
                "Target device" : "tap0ab4edec-71"
            }, 
            "from" : "1", 
            "object_name" : "vnic-network100", 
            "to" : "2"
        }, 
        {
            "attributes" : {
                "Model type" : "VirtIO"
            }, 
            "from" : "2", 
            "object_name" : "vNIC1-network100", 
            "to" : "3"
        }, 
        {
            "attributes" : {
                "VLAN vid" : "6", 
                "IP address" : "192.168.77.130", 
                "Target device" : "tap0ab4edec-13"
            }, 
            "from" : "301", 
            "object_name" : "vnic-network100", 
            "to" : "302"
        }, 
        {
            "attributes" : {
                "Model type" : "VirtIO"
            }, 
            "from" : "302", 
            "object_name" : "vNIC1-network100", 
            "to" : "303"
        }, 
        {
            "attributes" : {
                "OVS incoming port" : "qvo0ab4edec-13", 
                "DL VLAN" : "6", 
                "bridge outgoing port" : "qvb0ab4edec-13"
            }, 
            "from" : "303", 
            "object_name" : "bridge-network100", 
            "to" : "304"
        }, 
        {
            "attributes" : {
                "Network Type: " : "VLAN Trunk"
            }, 
            "from" : "304", 
            "object_name" : "vEdge-eth1", 
            "to" : "305"
        }, 
        {
            "attributes" : {
                "Segment: " : "VLAN 100"
            }, 
            "from" : "305", 
            "to" : "6", 
            "object_name" : "VLAN 100"
        }, 
        {
            "attributes" : {
                "VLAN vid" : "3", 
                "IP address" : "192.168.113.1", 
                "Target device" : "tap0ab4edec-33"
            }, 
            "from" : "301", 
            "object_name" : "vnic-network300", 
            "to" : "3002"
        }, 
        {
            "attributes" : {
                "Model type" : "VirtIO"
            }, 
            "from" : "3002", 
            "object_name" : "vNIC1-network300", 
            "to" : "3003"
        }, 
        {
            "attributes" : {
                "OVS incoming port" : "qvo0ab4edec-33", 
                "DL VLAN" : "300", 
                "bridge outgoing port" : "qvb0ab4edec-33"
            }, 
            "from" : "3003", 
            "object_name" : "bridge-network300", 
            "to" : "3004"
        }, 
        {
            "attributes" : {
                "Network Type: " : "VLAN Trunk"
            }, 
            "from" : "3004", 
            "object_name" : "vEdge-eth2", 
            "to" : "3005"
        }, 
        {
            "attributes" : {
                "Segment: " : "VLAN 300"
            }, 
            "from" : "3005", 
            "to" : "300", 
            "object_name" : "VLAN 300"
        }, 
        {
            "attributes" : {
                "VLAN vid" : "6", 
                "IP address" : "192.168.77.2", 
                "Target device" : "tap0ab4edec-72"
            }, 
            "from" : "101", 
            "object_name" : "vnic-network100", 
            "to" : "102"
        }, 
        {
            "attributes" : {
                "Model type" : "e1000"
            }, 
            "from" : "102", 
            "object_name" : "vNIC1-network100", 
            "to" : "3"
        }, 
        {
            "attributes" : {
                "OVS incoming port" : "qvo0ab4edec-74", 
                "DL VLAN" : "5", 
                "bridge outgoing port" : "qvb0ab4edec-74"
            }, 
            "from" : "3", 
            "object_name" : "bridge-network100", 
            "to" : "4"
        }, 
        {
            "attributes" : {
                "Network Type: " : "VLAN Trunk"
            }, 
            "from" : "4", 
            "object_name" : "vEdge-eth0", 
            "to" : "5"
        }, 
        {
            "attributes" : {
                "Segment: " : "VLAN 100"
            }, 
            "from" : "5", 
            "to" : "6", 
            "object_name" : "VLAN 100"
        }, 
        {
            "attributes" : {
                "Model type" : "VirtIO"
            }, 
            "from" : "1002", 
            "object_name" : "vNIC1-network100", 
            "to" : "1003"
        }, 
        {
            "attributes" : {
                "OVS incoming port" : "qvo0ab4edec-88", 
                "DL VLAN" : "88", 
                "bridge outgoing port" : "qvb0ab4edec-88"
            }, 
            "from" : "1003", 
            "object_name" : "bridge-host8-network100", 
            "to" : "1004"
        }, 
        {
            "attributes" : {
                "Network Type: " : "VLAN Trunk"
            }, 
            "from" : "1004", 
            "object_name" : "vEdge-eth1", 
            "to" : "1005"
        }, 
        {
            "attributes" : {
                "Segment: " : "VLAN 100"
            }, 
            "from" : "1005", 
            "to" : "6", 
            "object_name" : "VLAN 100"
        }, 
        {
            "attributes" : {
                "Model type" : "VirtIO", 
                "IP address" : "192.168.77.254"
            }, 
            "from" : "1112", 
            "object_name" : "vNIC1-network100", 
            "to" : "1113"
        }, 
        {
            "attributes" : {
                "OVS incoming port" : "qvo0ab4edec-77", 
                "DL VLAN" : "100", 
                "bridge outgoing port" : "qvb0ab4edec-77"
            }, 
            "from" : "1113", 
            "object_name" : "bridge-host7-network100", 
            "to" : "1114"
        }, 
        {
            "attributes" : {
                "Network Type: " : "VLAN Trunk"
            }, 
            "from" : "1114", 
            "object_name" : "vEdge-eth1", 
            "to" : "1115"
        }, 
        {
            "attributes" : {
                "Segment: " : "VLAN 100"
            }, 
            "from" : "1115", 
            "to" : "6", 
            "object_name" : "VLAN 100"
        }, 
        {
            "attributes" : {
                "Model type" : "e1000"
            }, 
            "from" : "1112", 
            "object_name" : "vNIC2-network200", 
            "to" : "1213"
        }, 
        {
            "attributes" : {
                "OVS incoming port" : "qvo0ab4edec-92", 
                "DL VLAN" : "200", 
                "bridge outgoing port" : "qvb0ab4edec-92"
            }, 
            "from" : "1213", 
            "object_name" : "bridge-host7-network200", 
            "to" : "1214"
        }, 
        {
            "attributes" : {
                "Network Type: " : "VLAN Trunk"
            }, 
            "from" : "1214", 
            "object_name" : "vEdge-eth2", 
            "to" : "1215"
        }, 
        {
            "attributes" : {
                "Segment: " : "VLAN 200"
            }, 
            "from" : "1215", 
            "to" : "200", 
            "object_name" : "VLAN 200"
        }, 
        {
            "attributes" : {
                "VLAN vid" : "747", 
                "IP address" : "192.168.78.1", 
                "Target device" : "tap0ab4edec-78"
            }, 
            "from" : "2001", 
            "object_name" : "vNIC1-network200", 
            "to" : "2002"
        }, 
        {
            "attributes" : {
                "Model type" : "e1000"
            }, 
            "from" : "2002", 
            "object_name" : "vNIC1-network200", 
            "to" : "2003"
        }, 
        {
            "attributes" : {
                "OVS incoming port" : "qvo0ab4edec-78", 
                "DL VLAN" : "200", 
                "bridge outgoing port" : "qvb0ab4edec-78"
            }, 
            "from" : "2003", 
            "object_name" : "bridge-network100", 
            "to" : "2004"
        }, 
        {
            "attributes" : {
                "Network Type: " : "VLAN Trunk"
            }, 
            "from" : "2004", 
            "object_name" : "vEdge-eth0", 
            "to" : "2005"
        }, 
        {
            "attributes" : {
                "Segment: " : "VLAN 200"
            }, 
            "from" : "2005", 
            "to" : "200", 
            "object_name" : "VLAN 200"
        }, 
        {
            "attributes" : {
                "VLAN vid" : "44", 
                "IP address" : "192.168.98.1", 
                "Target device" : "tap0ab4edec-49"
            }, 
            "from" : "401", 
            "object_name" : "vNIC1-network200", 
            "to" : "402"
        }, 
        {
            "attributes" : {
                "Model type" : "e1000"
            }, 
            "from" : "402", 
            "object_name" : "vNIC1-network200", 
            "to" : "403"
        }, 
        {
            "attributes" : {
                "OVS incoming port" : "qvo0ab4edec-49", 
                "DL VLAN" : "200", 
                "bridge outgoing port" : "qvb0ab4edec-49"
            }, 
            "from" : "403", 
            "object_name" : "bridge-network200", 
            "to" : "404"
        }, 
        {
            "attributes" : {
                "Network Type: " : "VLAN Trunk"
            }, 
            "from" : "404", 
            "object_name" : "vEdge-eth0", 
            "to" : "405"
        }, 
        {
            "attributes" : {
                "VLAN vid" : "93", 
                "IP address" : "192.168.78.10", 
                "Target device" : "tap0ab4edec-10"
            }, 
            "from" : "421", 
            "object_name" : "vNIC1-network100", 
            "to" : "422"
        }, 
        {
            "attributes" : {
                "Model type" : "virtIO"
            }, 
            "from" : "422", 
            "object_name" : "vNIC1-network100", 
            "to" : "423"
        }, 
        {
            "attributes" : {
                "OVS incoming port" : "qvo0ab4edec-10", 
                "DL VLAN" : "100", 
                "bridge outgoing port" : "qvb0ab4edec-10"
            }, 
            "from" : "423", 
            "object_name" : "bridge-network100", 
            "to" : "424"
        }, 
        {
            "attributes" : {
                "Network Type: " : "VLAN Trunk"
            }, 
            "from" : "424", 
            "object_name" : "vEdge-eth1", 
            "to" : "425"
        }, 
        {
            "attributes" : {
                "Segment: " : "VLAN 100"
            }, 
            "from" : "425", 
            "to" : "6", 
            "object_name" : "VLAN 100"
        }, 
        {
            "attributes" : {
                "Segment: " : "VLAN 200"
            }, 
            "from" : "405", 
            "to" : "200", 
            "object_name" : "VLAN 200"
        }, 
        {
            "attributes" : {
                "VLAN vid" : "56", 
                "IP address" : "192.168.98.2", 
                "Target device" : "tap0ab4edec-50"
            }, 
            "from" : "501", 
            "object_name" : "vNIC1-network200", 
            "to" : "502"
        }, 
        {
            "attributes" : {
                "Model type" : "e1000"
            }, 
            "from" : "502", 
            "object_name" : "vNIC1-network200", 
            "to" : "503"
        }, 
        {
            "attributes" : {
                "OVS incoming port" : "qvo0ab4edec-50", 
                "DL VLAN" : "200", 
                "bridge outgoing port" : "qvb0ab4edec-50"
            }, 
            "from" : "503", 
            "object_name" : "bridge-network200", 
            "to" : "504"
        }, 
        {
            "attributes" : {
                "Network Type: " : "VLAN Trunk"
            }, 
            "from" : "504", 
            "object_name" : "vEdge-eth0", 
            "to" : "505"
        }, 
        {
            "attributes" : {
                "Segment: " : "VLAN 200"
            }, 
            "from" : "505", 
            "to" : "200", 
            "object_name" : "VLAN 200"
        }, 
        {
            "attributes" : {
                "VLAN vid" : "56", 
                "IP address" : "192.168.98.3", 
                "Target device" : "tap0ab4edec-51"
            }, 
            "from" : "601", 
            "object_name" : "vNIC1-network200", 
            "to" : "602"
        }, 
        {
            "attributes" : {
                "Model type" : "e1000"
            }, 
            "from" : "602", 
            "object_name" : "vNIC1-network200", 
            "to" : "503"
        }, 
        {
            "attributes" : {
                "VLAN vid" : "56", 
                "IP address" : "192.168.98.4", 
                "Target device" : "tap0ab4edec-91"
            }, 
            "from" : "701", 
            "object_name" : "vNIC1-network200", 
            "to" : "702"
        }, 
        {
            "attributes" : {
                "Model type" : "e1000"
            }, 
            "from" : "702", 
            "object_name" : "vNIC1-network200", 
            "to" : "503"
        }, 
        {
            "attributes" : {
                "VLAN vid" : "57", 
                "IP address" : "192.168.98.6", 
                "Target device" : "tap0ab4edec-92"
            }, 
            "from" : "801", 
            "object_name" : "vNIC1-network200", 
            "to" : "802"
        }, 
        {
            "attributes" : {
                "Model type" : "e1000"
            }, 
            "from" : "802", 
            "object_name" : "vNIC1-network200", 
            "to" : "503"
        }, 
        {
            "attributes" : {
                "VLAN vid" : "77", 
                "IP address" : "176.16.98.1", 
                "Target device" : "tap0ab4edec-63"
            }, 
            "from" : "4001", 
            "object_name" : "vNIC1-network300", 
            "to" : "4002"
        }, 
        {
            "attributes" : {
                "Model type" : "e1000"
            }, 
            "from" : "4002", 
            "object_name" : "vNIC1-network300", 
            "to" : "4003"
        }, 
        {
            "attributes" : {
                "OVS incoming port" : "qvo0ab4edec-63", 
                "DL VLAN" : "300", 
                "bridge outgoing port" : "qvb0ab4edec-63"
            }, 
            "from" : "4003", 
            "object_name" : "bridge-network300", 
            "to" : "4004"
        }, 
        {
            "attributes" : {
                "Network Type: " : "VLAN Trunk"
            }, 
            "from" : "4004", 
            "object_name" : "vEdge-eth0", 
            "to" : "4005"
        }, 
        {
            "attributes" : {
                "Segment: " : "VLAN 300"
            }, 
            "from" : "4005", 
            "to" : "300", 
            "object_name" : "VLAN 300"
        }, 
        {
            "attributes" : {
                "VLAN vid" : "56", 
                "IP address" : "172.16.98.2", 
                "Target device" : "tap0ab4edec-58"
            }, 
            "from" : "5001", 
            "object_name" : "vNIC1-network300", 
            "to" : "5002"
        }, 
        {
            "attributes" : {
                "Model type" : "e1000"
            }, 
            "from" : "5002", 
            "object_name" : "vNIC1-network300", 
            "to" : "5003"
        }, 
        {
            "attributes" : {
                "OVS incoming port" : "qvo0ab4edec-58", 
                "DL VLAN" : "300", 
                "bridge outgoing port" : "qvb0ab4edec-58"
            }, 
            "from" : "5003", 
            "object_name" : "bridge-network300", 
            "to" : "5004"
        }, 
        {
            "attributes" : {
                "Network Type: " : "VLAN Trunk"
            }, 
            "from" : "5004", 
            "object_name" : "vEdge-eth0", 
            "to" : "5005"
        }, 
        {
            "attributes" : {
                "Segment: " : "VLAN 300"
            }, 
            "from" : "5005", 
            "to" : "300", 
            "object_name" : "VLAN 300"
        }, 
        {
            "attributes" : {
                "VLAN vid" : "66", 
                "IP address" : "172.16.98.3", 
                "Target device" : "tap0ab4edec-41"
            }, 
            "from" : "6001", 
            "object_name" : "vNIC1-network300", 
            "to" : "6002"
        }, 
        {
            "attributes" : {
                "Model type" : "e1000"
            }, 
            "from" : "6002", 
            "object_name" : "vNIC1-network300", 
            "to" : "5003"
        }, 
        {
            "attributes" : {
                "VLAN vid" : "14", 
                "IP address" : "172.16.98.4", 
                "Target device" : "tap0ab4edec-91"
            }, 
            "from" : "7001", 
            "object_name" : "vNIC1-network300", 
            "to" : "7002"
        }, 
        {
            "attributes" : {
                "Model type" : "e1000"
            }, 
            "from" : "7002", 
            "object_name" : "vNIC1-network300", 
            "to" : "5003"
        }, 
        {
            "attributes" : {
                "VLAN vid" : "57", 
                "IP address" : "172.16.98.6", 
                "Target device" : "tap0ab4edec-92"
            }, 
            "from" : "8001", 
            "object_name" : "vNIC1-network300", 
            "to" : "8002"
        }, 
        {
            "attributes" : {
                "Model type" : "e1000"
            }, 
            "from" : "8002", 
            "object_name" : "vNIC1-network300", 
            "to" : "5003"
        }, 
        {
            "attributes" : {
                "VLAN vid" : "29", 
                "IP address" : "172.16.98.7", 
                "Target device" : "tap0ab4edec-29"
            }, 
            "from" : "9001", 
            "object_name" : "vNIC1-network300", 
            "to" : "9002"
        }, 
        {
            "attributes" : {
                "Model type" : "e1000"
            }, 
            "from" : "9002", 
            "object_name" : "vNIC1-network300", 
            "to" : "5003"
        }
    ], 
    "environment" : "WebEX-Mirantis@Cisco", 
    "host" : "node-24", 
    "id" : "0651bc4f-9c03-4697-85ac-7b72aa9c4530", 
    "id_path" : "/WebEX-Mirantis@Cisco/WebEX-Mirantis@Cisco-projects/329e0576da594c62a911d0dccb1238a7/RegionOne-availability_zones/WebEx-RTP-Zone/node-24/node-24-instances/0651bc4f-9c03-4697-85ac-7b72aa9c4530", 
    "name" : "demo-vm-on-shared", 
    "show_in_tree" : true, 
    "type" : "instance", 
    "uuid" : "0651bc4f-9c03-4697-85ac-7b72aa9c4530"
}